Workbook

Sheet Veriler
A1: invoice_id | B1: customer | C1: quantity | D1: unit_price | E1: discount_percent | F1: tax_percent | H1: Özete git
A2: INV-001 | B2: Alpha | C2: 3 | D2: 19.99 | E2: 10 | F2: 20
A3: INV-002 | B3: Beta | C3: 2 | D3: 0.1 | E3: 0 | F3: 20
A4: INV-003 | B4: Gamma | C4: 1 | D4: 100 | E4: 100 | F4: 20
A5: INV-004 | B5: Delta | C5: 0 | D5: 500 | E5: 0 | F5: 20
A6: INV-005 | B6: Epsilon | C6: 1 | D6: 0.05 | E6: 0 | F6: 10
A7: INV-005 | B7: Epsilon duplicate | C7: 1 | D7: 0.05 | E7: 0 | F7: 10
A8: INV-006 | B8: Zeta | C8: 2 | D8: INVALID | E8: 0 | F8: 20

Sheet Hesaplar
A1: ID | B1: Matrah | C1: Indirim | D1: Net | E1: Vergi | F1: Brut | H1: Özete git
A2: =Veriler!A2 -> INV-001 | B2: =Veriler!C2*Veriler!D2 -> 59.97 | C2: =ROUND(B2*Veriler!E2/100,2) -> 6 | D2: =B2-C2 -> 53.97 | E2: =ROUND(D2*Veriler!F2/100,2) -> 10.79 | F2: =D2+E2 -> 64.76
A3: =Veriler!A3 -> INV-002 | B3: =Veriler!C3*Veriler!D3 -> 0.2 | C3: =ROUND(B3*Veriler!E3/100,2) -> 0 | D3: =B3-C3 -> 0.2 | E3: =ROUND(D3*Veriler!F3/100,2) -> 0.04 | F3: =D3+E3 -> 0.24
A4: =Veriler!A4 -> INV-003 | B4: =Veriler!C4*Veriler!D4 -> 100 | C4: =ROUND(B4*Veriler!E4/100,2) -> 100 | D4: =B4-C4 -> 0 | E4: =ROUND(D4*Veriler!F4/100,2) -> 0 | F4: =D4+E4 -> 0
A5: =Veriler!A5 -> INV-004 | B5: =Veriler!C5*Veriler!D5 -> 0 | C5: =ROUND(B5*Veriler!E5/100,2) -> 0 | D5: =B5-C5 -> 0 | E5: =ROUND(D5*Veriler!F5/100,2) -> 0 | F5: =D5+E5 -> 0
A6: =Veriler!A6 -> INV-005 | B6: =Veriler!C6*Veriler!D6 -> 0.05 | C6: =ROUND(B6*Veriler!E6/100,2) -> 0 | D6: =B6-C6 -> 0.05 | E6: =ROUND(D6*Veriler!F6/100,2) -> 0.01 | F6: =D6+E6 -> 0.06

Sheet Ozet
A1: Özet | D1: Veriler | E1: Hesaplar
A2: Net | B2: =SUM(Hesaplar!D2:D6) -> 54.22
A3: Vergi | B3: =SUM(Hesaplar!E2:E6) -> 10.84
A4: Brut | B4: =SUM(Hesaplar!F2:F6) -> 65.06
A7: Kapsam dışı satır 7 | B7: INV-005 ikinci kayıt / aynı kimliğin tekrarı; kullanıcı onayıyla hesap dışında.
A8: Kapsam dışı satır 8 | B8: INV-006 unit_price değeri INVALID; kullanıcı onayıyla hesap dışında.
